presencedb/__init__.py
presencedb/abc.py
presencedb/activity.py
presencedb/client.py
presencedb/constants.py
presencedb/enums.py
presencedb/errors.py
presencedb/http.py
presencedb/py.typed
presencedb/user.py
presencedb/utils.py
py_presencedb-2.0.3.dist-info/METADATA
py_presencedb-2.0.3.dist-info/WHEEL
py_presencedb-2.0.3.dist-info/licenses/AUTHORS.md
py_presencedb-2.0.3.dist-info/licenses/LICENSE
py_presencedb-2.0.3.dist-info/RECORD
