Metadata-Version: 2.4
Name: py-presencedb
Version: 2.0.3
Summary: API wrapper for the presencedb (undocumented) api
License-File: AUTHORS.md
License-File: LICENSE
Requires-Python: >=3.13
Requires-Dist: aiofile>=3.9.0
Requires-Dist: aiohttp>=3.11.11
Requires-Dist: humanize>=4.11.0
Requires-Dist: msgspec
Requires-Dist: yarl>=1.18.3
Provides-Extra: docs
Requires-Dist: mkdocs-material>=9.5.50; extra == 'docs'
Requires-Dist: mkdocs>=1.6.1; extra == 'docs'
Requires-Dist: mkdocstrings-python>=1.13.0; extra == 'docs'
Requires-Dist: mkdocstrings>=0.27.0; extra == 'docs'
Requires-Dist: typing-extensions>=4.12.2; extra == 'docs'
Provides-Extra: test
Requires-Dist: pytest-asyncio>=0.25.2; extra == 'test'
Requires-Dist: pytest-profiling>=1.8.1; extra == 'test'
Requires-Dist: pytest>=8.3.4; extra == 'test'
